ubcaerodesign/__init__.py
ubcaerodesign/logging_helper.py
ubcaerodesign/networking.py
ubcaerodesign-0.8.dist-info/LICENSE.txt
ubcaerodesign-0.8.dist-info/METADATA
ubcaerodesign-0.8.dist-info/WHEEL
ubcaerodesign-0.8.dist-info/RECORD
