Metadata-Version: 2.1
Name: ubcaerodesign
Version: 0.8
Summary: PyPi package for helper utlilities
License: AGPL
Author: Midora
Author-email: midorashiu@gmail.com
Requires-Python: ==3.9.*
Classifier: License :: Other/Proprietary License
Classifier: Programming Language :: Python :: 3
Classifier: Programming Language :: Python :: 3.9
Requires-Dist: zmq (>=0.0.0,<0.0.1)
